{"wiki_games.md":"ZybaJmPW","wiki_readme.md":"eXfcxSxQ","wiki_hacking-tools-and-software.md":"qCkHFC8J","wiki_beginners-guide-to-piracy.md":"lgniQND9","wiki_unsafesites.md":"d2SSaHgQ","contact-me.md":"UvkrClE6","features.md":"wRZoiJLC","wiki_windows tools.md":"x7m3Xbo-","wiki_music.md":"-hX6jCuy","wiki_index.md":"9V3k6_zY","wiki_security.md":"1I4GVZHg","index.md":"er3Ju4zX","wiki_ai.md":"UeVyQApy","wiki_moviesandtvshows.md":"w1JEY-3e","readme.md":"s8KSGjKk","wiki_adblocking.md":"ZgB9XY-f","wiki_extensions.md":"vmwYbWLI","wiki_software.md":"LsnQ_DFg","test.md":"9g4pqwNa","wiki_piracyglossary.md":"MimnfktM","whatsapp-channel.md":"7DVVj1Qq"}
